Metadata-Version: 1.1
Name: sub
Version: 0.0.5
Summary: Simple Tool to download Subtitles.
Home-page: http://github.com/leosartaj/sub
Author: Sartaj Singh
Author-email: singhsartaj94@gmail.com
License: MIT
Keywords: subtitles download movies tv shows
Platform: UNKNOWN
Classifier: Development Status :: 3 - Alpha
Classifier: Topic :: Utilities
Classifier: License :: OSI Approved :: MIT License
